LICENSE
MANIFEST.in
README.rst
requirements.txt
setup.cfg
setup.py
ckanext/__init__.py
ckanext/social/__init__.py
ckanext/social/plugin.py
ckanext/social/helpers/__init__.py
ckanext/social/helpers/helpers.py
ckanext/social/templates/base.html
ckanext/social/templates/snippets/social.html
ckanext/social/tests/__init__.py
ckanext/social/tests/test_plugin.py
ckanext_social.egg-info/PKG-INFO
ckanext_social.egg-info/SOURCES.txt
ckanext_social.egg-info/dependency_links.txt
ckanext_social.egg-info/entry_points.txt
ckanext_social.egg-info/namespace_packages.txt
ckanext_social.egg-info/top_level.txt