Metadata-Version: 1.1
Name: ckanext-social
Version: 0.0.1
Summary: Improved social sharing on CKAN
Home-page: https://github.com/edmondatto/ckanext-social
Author: Edmond Atto, Peter Musonye, Akash Baga
Author-email: edmond.atto@andela.com, peter.musonye@andela.com, akash.baga@andela.com
License: AGPL
Keywords: CKAN Social,CKAN,Social Sharing
Platform: UNKNOWN
Classifier: Development Status :: 4 - Beta
Classifier: License :: OSI Approved :: GNU Affero General Public License v3 or later (AGPLv3+)
Classifier: Programming Language :: Python :: 2.7
